{
  "city": "goa",
  "total": 5245,
  "updated_at": "2025-01-27T15:30:00.000000",
  "events": [
    {
      "id": "goa_new_year_2025_001",
      "title": "New Year Beach Party 2025",
      "description": "Epic New Year celebration on Baga Beach with top DJs and fireworks",
      "fromDate": "2025-01-01T20:00:00Z",
      "toDate": "2025-01-02T06:00:00Z",
      "tribe": "goa",
      "picture": "https://images.unsplash.com/photo-1571266028243-e68f797cf30e?w=800&h=600&fit=crop",
      "picture_thumbnail": "https://images.unsplash.com/photo-1571266028243-e68f797cf30e?w=300&h=200&fit=crop",
      "idPlace": "ChIJ_Beach_Baga_Goa",
      "placeName": "Baga Beach",
      "entryFee": 2500,
      "listTags": ["NEW YEAR", "BEACH PARTY", "FIREWORKS"],
      "viewsCount": 1250,
      "commentsCount": 89
    },
    {
      "id": "goa_techno_underground_002",
      "title": "Underground Techno Session",
      "description": "Deep underground techno vibes in secret Goa location",
      "fromDate": "2025-01-15T22:00:00Z",
      "toDate": "2025-01-16T08:00:00Z",
      "tribe": "goa",
      "picture": "https://images.unsplash.com/photo-1493225457124-a3eb161ffa5f?w=800&h=600&fit=crop",
      "picture_thumbnail": "https://images.unsplash.com/photo-1493225457124-a3eb161ffa5f?w=300&h=200&fit=crop",
      "idPlace": "ChIJ_Underground_Goa",
      "placeName": "Secret Underground Venue",
      "entryFee": 1500,
      "listTags": ["TECHNO", "UNDERGROUND", "LATE NIGHT"],
      "viewsCount": 567,
      "commentsCount": 34
    },
    {
      "id": "goa_trance_festival_003",
      "title": "PsyTrance Festival Goa 2025",
      "description": "3-day psychedelic trance festival with international artists",
      "fromDate": "2025-02-14T18:00:00Z",
      "toDate": "2025-02-17T06:00:00Z",
      "tribe": "goa",
      "picture": "https://images.unsplash.com/photo-1470229722913-7c0e2dbbafd3?w=800&h=600&fit=crop",
      "picture_thumbnail": "https://images.unsplash.com/photo-1470229722913-7c0e2dbbafd3?w=300&h=200&fit=crop",
      "idPlace": "ChIJ_Festival_Ground_Goa",
      "placeName": "Goa Festival Grounds",
      "entryFee": 8000,
      "listTags": ["PSYTRANCE", "FESTIVAL", "3-DAY EVENT"],
      "viewsCount": 2340,
      "commentsCount": 156
    },
    {
      "id": "goa_sunset_chill_004",
      "title": "Sunset Chill & Reggae",
      "description": "Relaxed sunset session with reggae vibes and beach cocktails",
      "fromDate": "2025-01-20T17:00:00Z",
      "toDate": "2025-01-20T22:00:00Z",
      "tribe": "goa",
      "picture": "https://images.unsplash.com/photo-1506905925346-21bda4d32df4?w=800&h=600&fit=crop",
      "picture_thumbnail": "https://images.unsplash.com/photo-1506905925346-21bda4d32df4?w=300&h=200&fit=crop",
      "idPlace": "ChIJ_Sunset_Beach_Goa",
      "placeName": "Sunset Beach Bar",
      "entryFee": 800,
      "listTags": ["SUNSET", "REGGAE", "CHILL"],
      "viewsCount": 445,
      "commentsCount": 23
    },
    {
      "id": "goa_electronic_night_005",
      "title": "Electronic Night with Live Sets",
      "description": "Cutting-edge electronic music with live performances",
      "fromDate": "2025-01-25T21:00:00Z",
      "toDate": "2025-01-26T04:00:00Z",
      "tribe": "goa",
      "picture": "https://images.unsplash.com/photo-1571330735066-03aaa9429d89?w=800&h=600&fit=crop",
      "picture_thumbnail": "https://images.unsplash.com/photo-1571330735066-03aaa9429d89?w=300&h=200&fit=crop",
      "idPlace": "ChIJ_Electronic_Venue_Goa",
      "placeName": "Electronic Club Goa",
      "entryFee": 2000,
      "listTags": ["ELECTRONIC", "LIVE SETS", "CLUB"],
      "viewsCount": 789,
      "commentsCount": 45
    },
    {
      "id": "goa_house_music_006",
      "title": "Deep House Sessions",
      "description": "Premium deep house music with international DJs",
      "fromDate": "2025-01-30T20:00:00Z",
      "toDate": "2025-01-31T03:00:00Z",
      "tribe": "goa",
      "picture": "https://images.unsplash.com/photo-1514525253161-7a46d19cd819?w=800&h=600&fit=crop",
      "picture_thumbnail": "https://images.unsplash.com/photo-1514525253161-7a46d19cd819?w=300&h=200&fit=crop",
      "idPlace": "ChIJ_House_Club_Goa",
      "placeName": "House Music Lounge",
      "entryFee": 1800,
      "listTags": ["DEEP HOUSE", "INTERNATIONAL DJS", "PREMIUM"],
      "viewsCount": 623,
      "commentsCount": 38
    },
    {
      "id": "goa_bollywood_night_007",
      "title": "Bollywood Night Special",
      "description": "Bollywood hits and dance performances with Indian DJs",
      "fromDate": "2025-02-05T19:00:00Z",
      "toDate": "2025-02-06T01:00:00Z",
      "tribe": "goa",
      "picture": "https://images.unsplash.com/photo-1578662996442-48f60103fc96?w=800&h=600&fit=crop",
      "picture_thumbnail": "https://images.unsplash.com/photo-1578662996442-48f60103fc96?w=300&h=200&fit=crop",
      "idPlace": "ChIJ_Bollywood_Venue_Goa",
      "placeName": "Bollywood Dance Hall",
      "entryFee": 1200,
      "listTags": ["BOLLYWOOD", "INDIAN MUSIC", "DANCE"],
      "viewsCount": 934,
      "commentsCount": 67
    },
    {
      "id": "goa_open_air_008",
      "title": "Open Air Jungle Party",
      "description": "Wild jungle party under the stars with fire shows",
      "fromDate": "2025-02-10T20:00:00Z",
      "toDate": "2025-02-11T06:00:00Z",
      "tribe": "goa",
      "picture": "https://images.unsplash.com/photo-1571019613454-1cb2f99b2d8b?w=800&h=600&fit=crop",
      "picture_thumbnail": "https://images.unsplash.com/photo-1571019613454-1cb2f99b2d8b?w=300&h=200&fit=crop",
      "idPlace": "ChIJ_Jungle_Venue_Goa",
      "placeName": "Jungle Party Grounds",
      "entryFee": 3000,
      "listTags": ["JUNGLE PARTY", "FIRE SHOW", "OPEN AIR"],
      "viewsCount": 1567,
      "commentsCount": 112
    }
  ]
}
